odoo/addons/sale_automatic_workflow_force_invoice/README.rst
odoo/addons/sale_automatic_workflow_force_invoice/__init__.py
odoo/addons/sale_automatic_workflow_force_invoice/__manifest__.py
odoo/addons/sale_automatic_workflow_force_invoice/data/automatic_workflow_data.xml
odoo/addons/sale_automatic_workflow_force_invoice/models/__init__.py
odoo/addons/sale_automatic_workflow_force_invoice/models/automatic_workflow_job.py
odoo/addons/sale_automatic_workflow_force_invoice/models/sale_workflow_process.py
odoo/addons/sale_automatic_workflow_force_invoice/static/description/icon.png
odoo/addons/sale_automatic_workflow_force_invoice/views/sale_workflow_process_view.xml
odoo_addon_sale_automatic_workflow_force_invoice-15.0.1.0.0.2.dist-info/METADATA
odoo_addon_sale_automatic_workflow_force_invoice-15.0.1.0.0.2.dist-info/WHEEL
odoo_addon_sale_automatic_workflow_force_invoice-15.0.1.0.0.2.dist-info/top_level.txt
odoo_addon_sale_automatic_workflow_force_invoice-15.0.1.0.0.2.dist-info/RECORD
